argmax.v
// argmax.v
// Find index of maximum among 10 signed inputs
module argmax(
    input             clk,
    input             reset,
    input      [15:0] in_data,   
    input             in_valid,  // high when in_data is valid
    input             start,
    output reg [3:0]  max_index, // 0..9 predicted digit
    output reg        done
);
  reg signed [15:0] max_val;
  reg [3:0] count;

  always @(posedge clk or posedge reset) begin
    if (reset) begin
      max_val   <= 0;
      max_index <= 0;
      count     <= 0;
      done      <= 0;
    end else if (start) begin
      if (in_valid) begin
        if (count == 0) begin
          max_val   <= in_data;
          max_index <= 0;
          count     <= 1;
          $display("[%0t] Argmax: Init value = 0x%0h (index 0)", $time, in_data);
        end else begin
          // Compare and update
          if ($signed(in_data) > $signed(max_val)) begin
            max_val   <= in_data;
            max_index <= count;
            $display("[%0t] Argmax: New Max = %0d at Index %0d", $time, in_data, count);
          end
          count <= count + 1;
          if (count == 9) begin
             done <= 1;
            $display("[%0t] Argmax DONE: Final Max = %0d at Index %0d", $time, max_val, max_index);
//            count <= 9;
            
          end
        end
      end
  end
  end
endmodule

fully_connected2.v
// Fully connected layer: 32 -> 10
module fully_connected2(
    input             clk,
    input             reset,
    input      [15:0] in_data,
    input             in_valid,
    input             start,
    output reg [15:0] out_data,
    output reg        out_valid,
    output reg        done
);
  integer i;
  reg signed [15:0] in_mem [0:31];        
  reg signed [15:0] weight_mem [0:319];   // 10*32 weights
  reg signed [15:0] bias_mem   [0:9];      // 10 biases
  reg signed [31:0] acc;

  reg [6:0]  in_cnt;   // input counter
  reg [3:0]  neuron;   // neuron index 0..9
  reg        computing;

  
  initial begin
    $readmemh("weights_l2.mem", weight_mem);  
    $readmemh("biases_l2.mem", bias_mem);    // 10 entries

    $display("weights_l2.mem loaded into fully_connected2.v");
    $display("biases_l2.mem loaded into fully_connected2.v");
    $display("First three values of weights_l2: 0x%0h, 0x%0h, 0x%0h", weight_mem[0], weight_mem[1], weight_mem[2]);
  end

  always @(posedge clk or posedge reset) begin
    if (reset) begin
      in_cnt    <= 0;
      neuron    <= 0;
      acc       <= 0;
      out_valid <= 0;
      done      <= 0;
      computing <= 0;
    end else if (start && !computing) begin
     
      if (in_valid && in_cnt < 32) begin
        in_mem[in_cnt] <= in_data;
        in_cnt <= in_cnt + 1;
        $display("FC2 in_data= %0d", in_data);
   
      end
      if (in_cnt == 32) begin
        computing <= 1;
        in_cnt    <= 0;
        neuron    <= 0;
        acc       <= 0;
        out_valid <= 0;
        done      <= 0;
      end
    end else if (computing) begin
      if (in_cnt < 32) begin
        acc <= acc + in_mem[in_cnt] * weight_mem[neuron*32 + in_cnt];
        in_cnt <= in_cnt + 1;
        out_valid <= 0;
      end else begin
        acc      <= acc + (bias_mem[neuron] <<< 15);
        out_data <= acc[30:15];
        out_valid<= 1;
       
       $display("[%0t] FC2: Neuron[%0d] Output = 0x%0h", $time, neuron, acc[30:15]);
   
        acc    <= 0;
        in_cnt <= 0;
        neuron <= neuron + 1;

        if (neuron == 9) begin    // check here tooo 
          done      <= 1;
          computing <= 0;
        end
      end
    end else begin
      out_valid <= 0;
      done      <= 0;
    end
  end
endmodule

relu.v
module relu(
    input         clk,
    input         reset,
    input  signed [15:0] in_data,
    input         in_valid,
    output reg signed [15:0] out_data,
    output reg    out_valid
);
  wire signed [15:0] relu_res = in_data[15] ? 16'sd0 : in_data;

  always @(posedge clk or posedge reset) begin
    if (reset) begin
      out_data  <= 0;
      out_valid <= 0;
    end else if (in_valid) begin
      out_data  <= relu_res;
      out_valid <= 1'b1;
      $display("[%0t] ReLU: Input=%0d, Output=%0d",
               $time, $signed(in_data), $signed(relu_res));
    end else begin
      out_valid <= 1'b0;
    end
  end
endmodule

fully_connected1.v
// fully_connected1.v


module fully_connected1(
    input              clk,
    input              reset,
    input              start,         
    input      [15:0]  in_data,       
    input              in_valid,      
    output reg [15:0]  out_data,      
    output reg         out_valid,     
    output reg         done           
);

  integer i;
  reg signed [15:0] in_mem [0:783];       
  reg signed [15:0] weight_mem [0:32*784-1]; 
  reg signed [15:0] bias_mem   [0:31];   

  reg signed [31:0] acc;  
  reg [9:0]  in_cnt;    
  reg [6:0]  neuron;    
  reg        computing;

  initial begin
    $readmemh("weights_l1.mem", weight_mem); // contains 32*784 entries
    $readmemh("biases_l1.mem", bias_mem);      // contains 32 entries

    $display("weights_l1.mem loaded into fully_connected1.v");
    $display("biases_l1.mem loaded into fully_connected1.v");
    $display("First three values of weights_l1: 0x%0h, 0x%0h, 0x%0h", weight_mem[0], weight_mem[1], weight_mem[2]);
  end

  always @(posedge clk or posedge reset) begin
    if (reset) begin
      in_cnt    <= 0;
      neuron    <= 0;
      acc       <= 0;
      out_data  <= 0;
      out_valid <= 0;
      done      <= 0;
      computing <= 0;
    end 
    else if (start && !computing) begin
      
      if (in_valid && in_cnt < 784) begin
        in_mem[in_cnt] <= in_data;
        in_cnt <= in_cnt + 1;
      end
      if (in_cnt == 784) begin
        
        computing <= 1;        // Start computing
        in_cnt    <= 0;
        neuron    <= 0;
        acc       <= 0;
      end
    end 
    else if (computing) begin
      
      if (in_cnt < 784) begin              // Multiply accumulate Loop
        acc <= acc + in_mem[in_cnt] * weight_mem[neuron*784 + in_cnt];
        in_cnt <= in_cnt + 1;
        out_valid <= 0;
      end 
      else begin

        acc <= acc + (bias_mem[neuron] << 15);
        out_data <= acc[30:15];    
        out_valid <= 1;
        
        $display("[%0t] FC1: Neuron[%0d] Output = 0x%0h", $time, neuron, acc[30:15]);

        // Prepare next neuron
        acc    <= 0;
        in_cnt <= 0;
        neuron <= neuron + 1;

        if (neuron == 31) begin  
          done      <= 1;
          computing <= 0;
        end 
      end
    end 
    else begin
      out_valid <= 0;
      done <= 0;
    end
  end
endmodule

Vivado project/ayush_final.srcs/sources_1/new/bram_loader.v
`timescale 1ns / 1ps
//////////////////////////////////////////////////////////////////////////////////
// Company: 
// Engineer: 
// 
// Create Date: 17.09.2025 04:37:20
// Design Name: 
// Module Name: bram_loader
// Project Name: 
// Target Devices: 
// Tool Versions: 
// Description: 
// 
// Dependencies: 
// 
// Revision:
// Revision 0.01 - File Created
// Additional Comments:
// 
//////////////////////////////////////////////////////////////////////////////////

// ============================================
// BRAM Loader for Weights/Biases/Images
// ============================================
module bram_loader #(
    parameter DATA_WIDTH = 16,
    parameter DEPTH      = 784,
    parameter FILE       = "weights_l1.mem"
)(
    input  wire clk,
    input  wire [$clog2(DEPTH)-1:0] addr,
    output reg  [DATA_WIDTH-1:0] dout
);
    reg [DATA_WIDTH-1:0] mem [0:DEPTH-1];

    initial begin
        $readmemh(FILE, mem);
    end

    always @(posedge clk) begin
        dout <= mem[addr];
    end
endmodule

flatten.v
// flatten.v
module flatten(
    input         clk,
    input         reset,
    input         start,          // start loading image
    output reg [15:0] pixel_out,   // Q15 pixel output
    output reg    pixel_valid,     // high when pixel_out is valid
    output reg    done             // high for one cycle after last pixel
);

//  reg signed [15:0] img_mem [0:783]; 
//  integer addr;
  
  localparam IMG_DEPTH = 784;
  reg [$clog2(IMG_DEPTH)-1:0] addr;
  wire [15:0] bram_dout;

  
  bram_loader #(
      .DATA_WIDTH(16),
      .DEPTH(IMG_DEPTH),
      .FILE("image.mem")
  ) U_img_bram (
      .clk(clk),
      .addr(addr),
      .dout(bram_dout)
  );
  
//  initial begin
//    $readmemh("image.mem", img_mem);
//    $display("image.mem loaded into flatten.v");
//    $display("First three values are: 0x%0h, 0x%0h, 0x%0h", img_mem[0], img_mem[1], img_mem[2]);
//  end

  reg running;

always @(posedge clk or posedge reset) begin
  if (reset) begin
    addr <= 0;
    running <= 0;
    pixel_out <= 0;
    pixel_valid <= 0;
    done <= 0;
  end else begin
    if (start && !running) begin
      // start new run
      running <= 1;
      addr <= 0;
      done <= 0;
    end else if (running) begin
      if (addr < IMG_DEPTH-1) begin
          pixel_out   <= bram_dout;
        pixel_valid <= 1;
        done <= 0;
        $display("[%0t] Flatten: Pixel[%0d] = 0x%0h", $time, addr, bram_dout);
        addr <= addr + 1;
      end else if (addr == 783) begin
        pixel_out  <= bram_dout;
        pixel_valid <= 1;
        done <= 1;
        $display("[%0t] Flatten: Pixel[%0d] = 0x%0h (last pixel) -> DONE asserted", $time, addr, bram_dout);
        running <= 0;   
      end
    end else begin
      pixel_valid <= 0;
      done <= 0;
    end
  end
end

endmodule

top_nn.v
// top_nn.v
module top_nn(
    input         clk,
    input         reset,
   
    output [3:0]  digit_out,    
    output        valid_out     
);
  // Internal wires connecting modules
  wire [15:0] pixel;
  wire        pix_valid, pix_done;
  reg         flatten_start;

  wire [15:0] fc1_out;
  wire        fc1_valid, fc1_done;
  reg         fc1_start;

  wire [15:0] relu_out;
  wire        relu_valid;

  wire [15:0] fc2_out;
  wire        fc2_valid, fc2_done;
  reg         fc2_start;

  wire [3:0]  arg_index;
  wire        arg_done;
  reg         arg_start;

  // Instantiate Flatten
  flatten U_flat(
    .clk(clk), .reset(reset), .start(flatten_start),
    .pixel_out(pixel), .pixel_valid(pix_valid), .done(pix_done)
  );

  // Instantiate Fully Connected Layer 1
  fully_connected1 U_fc1(
    .clk(clk), .reset(reset), .start(fc1_start),
    .in_data(pixel), .in_valid(pix_valid),
    .out_data(fc1_out), .out_valid(fc1_valid),
    .done(fc1_done)
  );

  // Instantiate ReLU
  relu U_relu(
    .clk(clk), .reset(reset),
    .in_data(fc1_out), .in_valid(fc1_valid),
    .out_data(relu_out), .out_valid(relu_valid)
  );

  // Instantiate Fully Connected Layer 2
  fully_connected2 U_fc2(
    .clk(clk), .reset(reset), .start(fc2_start),
    .in_data(relu_out), .in_valid(relu_valid),
    .out_data(fc2_out), .out_valid(fc2_valid),
    .done(fc2_done)
  );

  // Instantiate Argmax
  argmax U_arg(
    .clk(clk), .reset(reset), .start(arg_start),
    .in_data(fc2_out), .in_valid(fc2_valid),
    .max_index(arg_index), .done(arg_done)
  );

  // Output assignments
  assign digit_out = arg_index;
  assign valid_out = arg_done;
  
  
  
  // FSM to sequence the operations
  reg [2:0] state;
  localparam IDLE   = 3'd0,
             LOAD   = 3'd1,
             DO_FC1 = 3'd2,
             DO_FC2 = 3'd3,
             DO_ARG = 3'd4,
             DONE   = 3'd5;

    always @(posedge clk or posedge reset) begin
    if (reset) begin
      state <= IDLE;
      flatten_start <= 0; 
      fc1_start <= 0; 
      fc2_start <= 0; 
      arg_start <= 0;
    end else begin
      case (state)
        IDLE: begin
          flatten_start <= 1;  // keep high until pix_done
          $display("[%0t] Starting Flatten", $time);
          state <= LOAD;
        end

        LOAD: begin
          flatten_start <= 1;  // keep asserting start
          if (pix_done) begin
            flatten_start <= 0; // release after done
            fc1_start <= 1;
            $display("[%0t] Flatten done, starting FC1", $time);
            state <= DO_FC1;
          end
        end

        DO_FC1: begin
          fc1_start <= 1;  // keep high until fc1_done
          fc2_start <= 1;
          if (fc1_done) begin
            fc1_start <= 0;
            fc2_start <= 1;
            $display("[%0t] FC1 done, starting FC2", $time);
            state <= DO_FC2;
          end
        end

        DO_FC2: begin
          fc2_start <= 1;  // keep high until fc2_done
          arg_start <= 1;
          if (fc2_done) begin
            fc2_start <= 0;
            arg_start <= 1;
            $display("[%0t] FC2 done, starting Argmax", $time);
            state <= DO_ARG;
          end
        end

        DO_ARG: begin
          arg_start <= 1;  // keep high until arg_done
          if (arg_done) begin
            arg_start <= 0;
            $display("[%0t] Argmax done, digit=%0d", $time, arg_index);
            state <= DONE;
          end
        end

        DONE: begin
          state <= DONE;
        end
      endcase
    end
  end
endmodule

loader.v
`timescale 1ns/1ps
module tb_top_nn;

  reg clk, reset;
  wire [3:0] digit_out;
  wire valid_out;

  // DUT
  top_nn dut (
    .clk(clk),
    .reset(reset),
    .digit_out(digit_out),
    .valid_out(valid_out)
  );

  // Clock
  always #5 clk = ~clk;

  initial begin
    clk = 0; reset = 1;
    #20 reset = 0;

    // Simulation runs until prediction
    wait(valid_out);
    $display("Predicted Digit = %d at T=%0t", digit_out, $time);

    #50 $finish;
  end
endmodule

Vivado project/ayush_final.sim/sim_2/behav/xsim/waves.vcd
$date
   Wed Sep 17 04:42:35 2025
$end

$version
  2025.1.0
  $dumpfile ("waves.vcd") 
$end

$timescale
  1ps
$end

$scope module tb_top_nn $end
$var reg 1 ! clk $end
$var reg 1 " reset $end
$var wire 4 # digit_out [3:0] $end
$var wire 1 $ valid_out $end
$scope module dut $end
$var wire 1 % clk $end
$var wire 1 & reset $end
$var wire 4 # digit_out [3:0] $end
$var wire 1 $ valid_out $end
$var wire 16 ' pixel [15:0] $end
$var wire 1 ( pix_valid $end
$var wire 1 ) pix_done $end
$var reg 1 * flatten_start $end
$var wire 16 + fc1_out [15:0] $end
$var wire 1 , fc1_valid $end
$var wire 1 - fc1_done $end
$var reg 1 . fc1_start $end
$var wire 16 / relu_out [15:0] $end
$var wire 1 0 relu_valid $end
$var wire 16 1 fc2_out [15:0] $end
$var wire 1 2 fc2_valid $end
$var wire 1 3 fc2_done $end
$var reg 1 4 fc2_start $end
$var wire 4 5 arg_index [3:0] $end
$var wire 1 6 arg_done $end
$var reg 1 7 arg_start $end
$var reg 3 8 state [2:0] $end
$scope module U_flat $end
$var wire 1 % clk $end
$var wire 1 & reset $end
$var wire 1 9 start $end
$var reg 16 : pixel_out [15:0] $end
$var reg 1 ; pixel_valid $end
$var reg 1 < done $end
$var reg 10 = addr [9:0] $end
$var wire 16 > bram_dout [15:0] $end
$var reg 1 ? running $end
$scope module U_img_bram $end
$var wire 1 % clk $end
$var wire 10 @ addr [9:0] $end
$var reg 16 A dout [15:0] $end
$upscope $end
$upscope $end
$scope module U_fc1 $end
$var wire 1 % clk $end
$var wire 1 & reset $end
$var wire 1 B start $end
$var wire 16 ' in_data [15:0] $end
$var wire 1 ( in_valid $end
$var reg 16 C out_data [15:0] $end
$var reg 1 D out_valid $end
$var reg 1 E done $end
$var integer 32 F i [31:0] $end
$var reg 32 G acc [31:0] $end
$var reg 10 H in_cnt [9:0] $end
$var reg 7 I neuron [6:0] $end
$var reg 1 J computing $end
$upscope $end
$scope module U_relu $end
$var wire 1 % clk $end
$var wire 1 & reset $end
$var wire 16 + in_data [15:0] $end
$var wire 1 , in_valid $end
$var reg 16 K out_data [15:0] $end
$var reg 1 L out_valid $end
$var wire 16 M relu_res [15:0] $end
$upscope $end
$scope module U_fc2 $end
$var wire 1 % clk $end
$var wire 1 & reset $end
$var wire 16 / in_data [15:0] $end
$var wire 1 0 in_valid $end
$var wire 1 N start $end
$var reg 16 O out_data [15:0] $end
$var reg 1 P out_valid $end
$var reg 1 Q done $end
$var integer 32 R i [31:0] $end
$var reg 32 S acc [31:0] $end
$var reg 7 T in_cnt [6:0] $end
$var reg 4 U neuron [3:0] $end
$var reg 1 V computing $end
$upscope $end
$scope module U_arg $end
$var wire 1 % clk $end
$var wire 1 & reset $end
$var wire 16 1 in_data [15:0] $end
$var wire 1 2 in_valid $end
$var wire 1 W start $end
$var reg 4 X max_index [3:0] $end
$var reg 1 Y done $end
$var reg 16 Z max_val [15:0] $end
$var reg 4 [ count [3:0] $end
$upscope $end
$upscope $end
$upscope $end
$enddefinitions $end

#0
$dumpvars
0!
1"
b0 #
0$
0%
1&
b0 '
0(
0)
0*
b0 +
0,
0-
0.
b0 /
00
bx 1
02
03
04
b0 5
06
07
b0 8
09
b0 :
0;
0<
b0 =
bx >
0?
b0 @
bx A
0B
b0 C
0D
0E
bx F
b0 G
b0 H
b0 I
0J
b0 K
0L
b0 M
0N
bx O
0P
0Q
bx R
b0 S
b0 T
b0 U
0V
0W
b0 X
0Y
b0 Z
b0 [
$end

#5000
1!
1%
b100100001001 >
b100100001001 A

#10000
0!
0%

#15000
1!
1%

#20000
0!
0"
0%
0&

#25000
1!
1%
1*
b1 8
19

#30000
0!
0%

#35000
1!
1%
1?

#40000
0!
0%

#45000
1!
1%
b100100001001 '
1(
b100100001001 :
1;
b1 =
b1 @

#50000
0!
0%

#55000
1!
1%
b10 =
b10100000101 >
b10 @
b10100000101 A

#60000
0!
0%

#65000
1!
1%
b10100000101 '
b10100000101 :
b11 =
b11 @

#70000
0!
0%

#75000
1!
1%
b100 =
b100 @

#80000
0!
0%

#85000
1!
1%
b101 =
b101 @

#90000
0!
0%

#95000
1!
1%
b110 =
b110 @

#100000
0!
0%

#105000
1!
1%
b111 =
b111 @

#110000
0!
0%

#115000
1!
1%
b1000 =
b1000 @

#120000
0!
0%

#125000
1!
1%
b1001 =
b1001 @

#130000
0!
0%

#135000
1!
1%
b1010 =
b1010 @

#140000
0!
0%

#145000
1!
1%
b1011 =
b1011 @

#150000
0!
0%

#155000
1!
1%
b1100 =
b1100 @

#160000
0!
0%

#165000
1!
1%
b1101 =
b1101 @

#170000
0!
0%

#175000
1!
1%
b1110 =
b1110 @

#180000
0!
0%

#185000
1!
1%
b1111 =
b1111 @

#190000
0!
0%

#195000
1!
1%
b10000 =
b10000 @

#200000
0!
0%

#205000
1!
1%
b10001 =
b10001 @

#210000
0!
0%

#215000
1!
1%
b10010 =
b10010 @

#220000
0!
0%

#225000
1!
1%
b10011 =
b10011 @

#230000
0!
0%

#235000
1!
1%
b10100 =
b10100 @

#240000
0!
0%

#245000
1!
1%
b10101 =
b10101 @

#250000
0!
0%

#255000
1!
1%
b10110 =
b10110 @

#260000
0!
0%

#265000
1!
1%
b10111 =
b10111 @

#270000
0!
0%

#275000
1!
1%
b11000 =
b11000 @

#280000
0!
0%

#285000
1!
1%
b11001 =
b11001 @

#290000
0!
0%

#295000
1!
1%
b11010 =
b11010 @

#300000
0!
0%

#305000
1!
1%
b11011 =
b11011 @

#310000
0!
0%

#315000
1!
1%
b11100 =
b110010001101 >
b11100 @
b110010001101 A

#320000
0!
0%

#325000
1!
1%
b110010001101 '
b110010001101 :
b11101 =
b10010000101 >
b11101 @
b10010000101 A

#330000
0!
0%

#335000
1!
1%
b10010000101 '
b10010000101 :
b11110 =
b0 >
b11110 @
b0 A

#340000
0!
0%

#345000
1!
1%
b0 '
b0 :
b11111 =
b11111 @

#350000
0!
0%

#355000
1!
1%
b100000 =
b100000 @

#360000
0!
0%

#365000
1!
1%
b100001 =
b100001 @

#370000
0!
0%

#375000
1!
1%
b100010 =
b100010 @

#380000
0!
0%

#385000
1!
1%
b100011 =
b100011 @

#390000
0!
0%

#395000
1!
1%
b100100 =
b100100 @

#400000
0!
0%

#405000
1!
1%
b100101 =
b100101 @

#410000
0!
0%

#415000
1!
1%
b100110 =
b100110 @

#420000
0!
0%

#425000
1!
1%
b100111 =
b100111 @

#430000
0!
0%

#435000
1!
1%
b101000 =
b101000 @

#440000
0!
0%

#445000
1!
1%
b101001 =
b101001 @

#450000
0!
0%

#455000
1!
1%
b101010 =
b101010 @

#460000
0!
0%

#465000
1!
1%
b101011 =
b101011 @

#470000
0!
0%

#475000
1!
1%
b101100 =
b101100 @

#480000
0!
0%

#485000
1!
1%
b101101 =
b101101 @

#490000
0!
0%

#495000
1!
1%
b101110 =
b101110 @

#500000
0!
0%

#505000
1!
1%
b101111 =
b101111 @

#510000
0!
0%

#515000
1!
1%
b110000 =
b110000 @

#520000
0!
0%

#525000
1!
1%
b110001 =
b110001 @

#530000
0!
0%

#535000
1!
1%
b110010 =
b110010 @

#540000
0!
0%

#545000
1!
1%
b110011 =
b110011 @

#550000
0!
0%

#555000
1!
1%
b110100 =
b110100 @

#560000
0!
0%

#565000
1!
1%
b110101 =
b110101 @

#570000
0!
0%

#575000
1!
1%
b110110 =
b110110 @

#580000
0!
0%

#585000
1!
1%
b110111 =
b110111 @

#590000
0!
0%

#595000
1!
1%
b111000 =
b11110001000 >
b111000 @
b11110001000 A

#600000
0!
0%

#605000
1!
1%
b11110001000 '
b11110001000 :
b111001 =
b10100000101 >
b111001 @
b10100000101 A

#610000
0!
0%

#615000
1!
1%
b10100000101 '
b10100000101 :
b111010 =
b0 >
b111010 @
b0 A

#620000
0!
0%

#625000
1!
1%
b0 '
b0 :
b111011 =
b111011 @

#630000
0!
0%

#635000
1!
1%
b111100 =
b111100 @

#640000
0!
0%

#645000
1!
1%
b111101 =
b111101 @

#650000
0!
0%

#655000
1!
1%
b111110 =
b111110 @

#660000
0!
0%

#665000
1!
1%
b111111 =
b111111 @

#670000
0!
0%

#675000
1!
1%
b1000000 =
b1000000 @

#680000
0!
0%

#685000
1!
1%
b1000001 =
b1000001 @

#690000
0!
0%

#695000
1!
1%
b1000010 =
b1000010 @

#700000
0!
0%

#705000
1!
1%
b1000011 =
b1000011 @

#710000
0!
0%

#715000
1!
1%
b1000100 =
b1000100 @

#720000
0!
0%

#725000
1!
1%
b1000101 =
b1000101 @

#730000
0!
0%

#735000
1!
1%
b1000110 =
b1000110 @

#740000
0!
0%

#745000
1!
1%
b1000111 =
b1000111 @

#750000
0!
0%

#755000
1!
1%
b1001000 =
b1001000 @

#760000
0!
0%

#765000
1!
1%
b1001001 =
b1001001 @

#770000
0!
0%

#775000
1!
1%
b1001010 =
b1001010 @

#780000
0!
0%

#785000
1!
1%
b1001011 =
b1001011 @

#790000
0!
0%

#795000
1!
1%
b1001100 =
b1001100 @

#800000
0!
0%

#805000
1!
1%
b1001101 =
b1001101 @

#810000
0!
0%

#815000
1!
1%
b1001110 =
b1001110 @

#820000
0!
0%

#825000
1!
1%
b1001111 =
b1001111 @

#830000
0!
0%

#835000
1!
1%
b1010000 =
b1010000 @

#840000
0!
0%

#845000
1!
1%
b1010001 =
b1010001 @

#850000
0!
0%

#855000
1!
1%
b1010010 =
b1010010 @

#860000
0!
0%

#865000
1!
1%
b1010011 =
b1010011 @

#870000
0!
0%

#875000
1!
1%
b1010100 =
b100000001000 >
b1010100 @
b100000001000 A

#880000
0!
0%

#885000
1!
1%
b100000001000 '
b100000001000 :
b1010101 =
b10100000101 >
b1010101 @
b10100000101 A

#890000
0!
0%

#895000
1!
1%
b10100000101 '
b10100000101 :
b1010110 =
b0 >
b1010110 @
b0 A

#900000
0!
0%

#905000
1!
1%
b0 '
b0 :
b1010111 =
b1010111 @

#910000
0!
0%

#915000
1!
1%
b1011000 =
b1011000 @

#920000
0!
0%

#925000
1!
1%
b1011001 =
b1011001 @

#930000
0!
0%

#935000
1!
1%
b1011010 =
b1011010 @

#940000
0!
0%

#945000
1!
1%
b1011011 =
b1011011 @

#950000
0!
0%

#955000
1!
1%
b1011100 =
b1011100 @

#960000
0!
0%

#965000
1!
1%
b1011101 =
b1011101 @

#970000
0!
0%

#975000
1!
1%
b1011110 =
b1011110 @

#980000
0!
0%

#985000
1!
1%
b1011111 =
b1011111 @

#990000
0!
0%

#995000
1!
1%
b1100000 =
b1100000 @

#1000000
0!
0%

#1005000
1!
1%
b1100001 =
b1100001 @

#1010000
0!
0%

#1015000
1!
1%
b1100010 =
b1100010 @

#1020000
0!
0%

#1025000
1!
1%
b1100011 =
b1100011 @

#1030000
0!
0%

#1035000
1!
1%
b1100100 =
b1100100 @

#1040000
0!
0%

#1045000
1!
1%
b1100101 =
b1100101 @

#1050000
0!
0%

#1055000
1!
1%
b1100110 =
b1100110 @

#1060000
0!
0%

#1065000
1!
1%
b1100111 =
b1100111 @

#1070000
0!
0%

#1075000
1!
1%
b1101000 =
b1101000 @

#1080000
0!
0%

#1085000
1!
1%
b1101001 =
b1101001 @

#1090000
0!
0%

#1095000
1!
1%
b1101010 =
b1101010 @

#1100000
0!
0%

#1105000
1!
1%
b1101011 =
b1101011 @

#1110000
0!
0%

#1115000
1!
1%
b1101100 =
b1101100 @

#1120000
0!
0%

#1125000
1!
1%
b1101101 =
b1101101 @

#1130000
0!
0%

#1135000
1!
1%
b1101110 =
b1101110 @

#1140000
0!
0%

#1145000
1!
1%
b1101111 =
b1101111 @

#1150000
0!
0%

#1155000
1!
1%
b1110000 =
b100000001000 >
b1110000 @
b100000001000 A

#1160000
0!
0%

#1165000
1!
1%
b100000001000 '
b100000001000 :
b1110001 =
b10100000101 >
b1110001 @
b10100000101 A

#1170000
0!
0%

#1175000
1!
1%
b10100000101 '
b10100000101 :
b1110010 =
b0 >
b1110010 @
b0 A

#1180000
0!
0%

#1185000
1!
1%
b0 '
b0 :
b1110011 =
b1110011 @

#1190000
0!
0%

#1195000
1!
1%
b1110100 =
b1110100 @

#1200000
0!
0%

#1205000
1!
1%
b1110101 =
b1110101 @

#1210000
0!
0%

#1215000
1!
1%
b1110110 =
b1110110 @

#1220000
0!
0%

#1225000
1!
1%
b1110111 =
b1110111 @

#1230000
0!
0%

#1235000
1!
1%
b1111000 =
b1111000 @

#1240000
0!
0%

#1245000
1!
1%
b1111001 =
b1111001 @

#1250000
0!
0%

#1255000
1!
1%
b1111010 =
b1111010 @

#1260000
0!
0%

#1265000
1!
1%
b1111011 =
b1111011 @

#1270000
0!
0%

#1275000
1!
1%
b1111100 =
b1111100 @

#1280000
0!
0%

#1285000
1!
1%
b1111101 =
b1111101 @

#1290000
0!
0%

#1295000
1!
1%
b1111110 =
b1111110 @

#1300000
0!
0%

#1305000
1!
1%
b1111111 =
b1111111 @

#1310000
0!
0%

#1315000
1!
1%
b10000000 =
b10000000 @

#1320000
0!
0%

#1325000
1!
1%
b10000001 =
b10000001 @

#1330000
0!
0%

#1335000
1!
1%
b10000010 =
b10000010 @

#1340000
0!
0%

#1345000
1!
1%
b10000011 =
b10000011 @

#1350000
0!
0%

#1355000
1!
1%
b10000100 =
b10000100 @

#1360000
0!
0%

#1365000
1!
1%
b10000101 =
b10000101 @

#1370000
0!
0%

#1375000
1!
1%
b10000110 =
b10000110 @

#1380000
0!
0%

#1385000
1!
1%
b10000111 =
b10000111 @

#1390000
0!
0%

#1395000
1!
1%
b10001000 =
b10001000 @

#1400000
0!
0%

#1405000
1!
1%
b10001001 =
b10001001 @

#1410000
0!
0%

#1415000
1!
1%
b10001010 =
b10001010 @

#1420000
0!
0%

#1425000
1!
1%
b10001011 =
b10001011 @

#1430000
0!
0%

#1435000
1!
1%
b10001100 =
b100000001000 >
b10001100 @
b100000001000 A

#1440000
0!
0%

#1445000
1!
1%
b100000001000 '
b100000001000 :
b10001101 =
b10010000101 >
b10001101 @
b10010000101 A

#1450000
0!
0%

#1455000
1!
1%
b10010000101 '
b10010000101 :
b10001110 =
b0 >
b10001110 @
b0 A

#1460000
0!
0%

#1465000
1!
1%
b0 '
b0 :
b10001111 =
b10001111 @

#1470000
0!
0%

#1475000
1!
1%
b10010000 =
b10010000 @

#1480000
0!
0%

#1485000
1!
1%
b10010001 =
b10010001 @

#1490000
0!
0%

#1495000
1!
1%
b10010010 =
b10010010 @

#1500000
0!
0%

#1505000
1!
1%
b10010011 =
b10010011 @

#1510000
0!
0%

#1515000
1!
1%
b10010100 =
b10010100 @

#1520000
0!
0%

#1525000
1!
1%
b10010101 =
b10010101 @

#1530000
0!
0%

#1535000
1!
1%
b10010110 =
b10010110 @

#1540000
0!
0%

#1545000
1!
1%
b10010111 =
b10010111 @

#1550000
0!
0%

#1555000
1!
1%
b10011000 =
b10011000 @

#1560000
0!
0%

#1565000
1!
1%
b10011001 =
b10011001 @

#1570000
0!
0%

#1575000
1!
1%
b10011010 =
b10011010 @

#1580000
0!
0%

#1585000
1!
1%
b10011011 =
b10011011 @

#1590000
0!
0%

#1595000
1!
1%
b10011100 =
b10011100 @

#1600000
0!
0%

#1605000
1!
1%
b10011101 =
b10011101 @

#1610000
0!
0%

#1615000
1!
1%
b10011110 =
b10011110 @

#1620000
0!
0%

#1625000
1!
1%
b10011111 =
b10011111 @

#1630000
0!
0%

#1635000
1!
1%
b10100000 =
b10100000 @

#1640000
0!
0%

#1645000
1!
1%
b10100001 =
b10100001 @

#1650000
0!
0%

#1655000
1!
1%
b10100010 =
b10100010 @

#1660000
0!
0%

#1665000
1!
1%
b10100011 =
b10100011 @

#1670000
0!
0%

#1675000
1!
1%
b10100100 =
b10100100 @

#1680000
0!
0%

#1685000
1!
1%
b10100101 =
b10100101 @

#1690000
0!
0%

#1695000
1!
1%
b10100110 =
b10100110 @

#1700000
0!
0%

#1705000
1!
1%
b10100111 =
b10100111 @

#1710000
0!
0%

#1715000
1!
1%
b10101000 =
b100000001000 >
b10101000 @
b100000001000 A

#1720000
0!
0%

#1725000
1!
1%
b100000001000 '
b100000001000 :
b10101001 =
b10100000101 >
b10101001 @
b10100000101 A

#1730000
0!
0%

#1735000
1!
1%
b10100000101 '
b10100000101 :
b10101010 =
b0 >
b10101010 @
b0 A

#1740000
0!
0%

#1745000
1!
1%
b0 '
b0 :
b10101011 =
b10101011 @

#1750000
0!
0%

#1755000
1!
1%
b10101100 =
b10101100 @

#1760000
0!
0%

#1765000
1!
1%
b10101101 =
b10101101 @

#1770000
0!
0%

#1775000
1!
1%
b10101110 =
b10101110 @

#1780000
0!
0%

#1785000
1!
1%
b10101111 =
b1000000010 >
b10101111 @
b1000000010 A

#1790000
0!
0%

#1795000
1!
1%
b1000000010 '
b1000000010 :
b10110000 =
b10110000110 >
b10110000 @
b10110000110 A

#1800000
0!
0%

#1805000
1!
1%
b10110000110 '
b10110000110 :
b10110001 =
b10100000101 >
b10110001 @
b10100000101 A

#1810000
0!
0%

#1815000
1!
1%
b10100000101 '
b10100000101 :
b10110010 =
b10010000101 >
b10110010 @
b10010000101 A

#1820000
0!
0%

#1825000
1!
1%
b10010000101 '
b10010000101 :
b10110011 =
b110000010 >
b10110011 @
b110000010 A

#1830000
0!
0%

#1835000
1!
1%
b110000010 '
b110000010 :
b10110100 =
b0 >
b10110100 @
b0 A

#1840000
0!
0%

#1845000
1!
1%
b0 '
b0 :
b10110101 =
b10110101 @

#1850000
0!
0%

#1855000
1!
1%
b10110110 =
b10110110 @

#1860000
0!
0%

#1865000
1!
1%
b10110111 =
b10110111 @

#1870000
0!
0%

#1875000
1!
1%
b10111000 =
b10111000 @

#1880000
0!
0%

#1885000
1!
1%
b10111001 =
b10111001 @

